{
  "bg": 149, 
  "temp": "absolute", 
  "snoozeBG": 204, 
  "predBGs": {
    "COB": [
      149, 
      146, 
      143, 
      139, 
      135, 
      130, 
      124, 
      118, 
      111, 
      104, 
      96, 
      87, 
      78, 
      69, 
      62, 
      54, 
      48, 
      42, 
      39, 
      39, 
      39, 
      39, 
      39, 
      39, 
      39, 
      39, 
      39, 
      39, 
      39, 
      39, 
      39, 
      39, 
      39, 
      39, 
      39, 
      39, 
      39, 
      42, 
      45, 
      49, 
      52, 
      55, 
      58
    ], 
    "aCOB": [
      149, 
      152, 
      155, 
      157, 
      158, 
      159, 
      158, 
      157, 
      156, 
      154, 
      151, 
      147, 
      143, 
      139, 
      136, 
      133, 
      131, 
      130, 
      129, 
      129, 
      129, 
      130, 
      131, 
      132, 
      134, 
      137, 
      140, 
      143, 
      147, 
      152, 
      157, 
      162, 
      168, 
      174, 
      180, 
      186, 
      192, 
      198, 
      204, 
      210, 
      215, 
      221, 
      226
    ], 
    "IOB": [
      149, 
      146, 
      142, 
      138, 
      132, 
      125, 
      118, 
      109, 
      100, 
      90, 
      78, 
      66, 
      53, 
      41, 
      39
    ]
  }, 
  "reason": "COB: 77, Dev: 21, BGI: -6.57, ISF: 82, Target: 80; Eventual BG 58 < 80, bolus snooze: eventual BG range 58-204, temp 0.775 ~ req 0.775U/hr", 
  "COB": 77, 
  "eventualBG": 58, 
  "tick": -3, 
  "IOB": 2.892
}