[
  {
    "created_at": "2016-11-18T18:31:23.626Z", 
    "mmtune": {
      "scanDetails": [
        [
          "916.564", 
          5, 
          -54
        ], 
        [
          "916.588", 
          5, 
          -52
        ], 
        [
          "916.612", 
          5, 
          -51
        ], 
        [
          "916.636", 
          5, 
          -53
        ], 
        [
          "916.660", 
          5, 
          -53
        ], 
        [
          "916.684", 
          5, 
          -56
        ]
      ], 
      "setFreq": 916.612, 
      "usedDefault": false, 
      "timestamp": "2016-11-18T18:28:53.000Z"
    }, 
    "pump": {
      "battery": {
        "status": "normal", 
        "voltage": 1.54
      }, 
      "status": {
        "status": "normal", 
        "timestamp": "2016-11-18T18:29:18.000Z", 
        "bolusing": false, 
        "suspended": false
      }, 
      "reservoir": 63.65, 
      "clock": "2016-11-18T10:29:09-08:00"
    }, 
    "openaps": {
      "suggested": {
        "bg": 160, 
        "temp": "absolute", 
        "snoozeBG": 119, 
        "timestamp": "2016-11-18T18:31:06.000Z", 
        "predBGs": {
          "IOB": [
            160, 
            157, 
            153, 
            150, 
            147, 
            143, 
            140, 
            136, 
            133, 
            129, 
            126, 
            123, 
            120, 
            117, 
            114, 
            112, 
            109, 
            107, 
            105, 
            104, 
            102, 
            101, 
            100, 
            99, 
            98, 
            97, 
            97, 
            96, 
            96, 
            95, 
            95, 
            94, 
            94, 
            94, 
            93
          ]
        }, 
        "reason": "COB: 0, Dev: 19, BGI: -6.13, ISF: 73, Target: 80; Eventual BG 119 >= 80, temp 1.175<1.35U/hr, but 26m left and 1.175 ~ req 1.35U/hr: no action required", 
        "COB": 0, 
        "eventualBG": 119, 
        "tick": -3, 
        "IOB": 0.814
      }, 
      "iob": {
        "netbasalinsulin": 1.8, 
        "timestamp": "2016-11-18T18:29:09.000Z", 
        "activity": 0.0167, 
        "basaliob": 0.812, 
        "hightempinsulin": 1.95, 
        "bolussnooze": 0, 
        "iob": 0.814
      }, 
      "enacted": {
        "bg": 163, 
        "temp": "absolute", 
        "snoozeBG": 114, 
        "recieved": true, 
        "reason": "COB: 0, Dev: 19, BGI: -6.41, ISF: 74, Target: 80; Eventual BG 114 >= 80, temp 0.675<1.2U/hr", 
        "rate": 1.175, 
        "COB": 0, 
        "eventualBG": 114, 
        "timestamp": "2016-11-18T18:25:39.000Z", 
        "duration": 30, 
        "tick": -2, 
        "IOB": 0.912
      }
    }, 
    "uploader": {
      "battery": 77, 
      "batteryVoltage": 3946
    }, 
    "device": "openaps://indy-e1", 
    "_id": "582f48fb0e76b898408f19db"
  }
]