[
  {
    "created_at": "2016-11-17T22:19:49.753Z", 
    "mmtune": {
      "scanDetails": [
        [
          "916.540", 
          4, 
          -93
        ], 
        [
          "916.564", 
          5, 
          -82
        ], 
        [
          "916.588", 
          5, 
          -80
        ], 
        [
          "916.612", 
          5, 
          -77
        ], 
        [
          "916.636", 
          5, 
          -66
        ], 
        [
          "916.660", 
          5, 
          -69
        ], 
        [
          "916.684", 
          5, 
          -66
        ]
      ], 
      "setFreq": 916.684, 
      "usedDefault": false, 
      "timestamp": "2016-11-17T22:16:57.000Z"
    }, 
    "pump": {
      "battery": {
        "status": "normal", 
        "voltage": 1.53
      }, 
      "status": {
        "status": "normal", 
        "timestamp": "2016-11-17T22:17:10.000Z", 
        "bolusing": false, 
        "suspended": false
      }, 
      "reservoir": 89.475, 
      "clock": "2016-11-17T14:17:01-08:00"
    }, 
    "openaps": {
      "suggested": {
        "bg": 116, 
        "temp": "absolute", 
        "snoozeBG": 12, 
        "timestamp": "2016-11-17T22:19:40.000Z", 
        "predBGs": {
          "COB": [
            116, 
            110, 
            102, 
            94, 
            85, 
            75, 
            65, 
            55, 
            46, 
            39, 
            39, 
            39, 
            39, 
            39, 
            39, 
            39, 
            39, 
            39, 
            39, 
            39, 
            39, 
            39, 
            39, 
            39, 
            39, 
            39, 
            39, 
            39, 
            39, 
            39, 
            39, 
            39, 
            39, 
            39, 
            39, 
            39, 
            42, 
            45, 
            48, 
            51, 
            55, 
            57, 
            60
          ], 
          "aCOB": [
            116, 
            116, 
            114, 
            111, 
            108, 
            103, 
            98, 
            94, 
            90, 
            86, 
            84, 
            81, 
            79, 
            78, 
            78, 
            78, 
            79, 
            80, 
            82, 
            84, 
            87, 
            91, 
            95, 
            99, 
            104, 
            110, 
            116, 
            122, 
            128, 
            134, 
            140, 
            146, 
            151, 
            157, 
            162, 
            167, 
            171, 
            176, 
            180, 
            184, 
            188, 
            192, 
            195
          ], 
          "IOB": [
            116, 
            109, 
            101, 
            92, 
            82, 
            70, 
            58, 
            47, 
            39, 
            39, 
            39, 
            39, 
            39
          ]
        }, 
        "reason": "COB: 52, Dev: 16, BGI: -10.31, ISF: 87, Target: 114; Eventual BG 60 < 114, setting -4.1U/hr, but 28m left and 0 ~ req 0U/hr: no action required", 
        "COB": 52, 
        "eventualBG": 60, 
        "tick": -7, 
        "IOB": 2.444
      }, 
      "iob": {
        "netbasalinsulin": 0.25, 
        "timestamp": "2016-11-17T22:17:01.000Z", 
        "activity": 0.0237, 
        "basaliob": 0.327, 
        "hightempinsulin": 0.8, 
        "bolussnooze": 0.713, 
        "iob": 2.444
      }, 
      "enacted": {
        "bg": 124, 
        "temp": "absolute", 
        "snoozeBG": 24, 
        "recieved": true, 
        "reason": "COB: 52, Dev: 11, BGI: -9.66, ISF: 87, Target: 114; Eventual BG 39 < 114, setting -3.55U/hr", 
        "rate": 0, 
        "COB": 52, 
        "eventualBG": 39, 
        "timestamp": "2016-11-17T22:15:43.000Z", 
        "duration": 30, 
        "tick": -7, 
        "IOB": 2.58
      }
    }, 
    "uploader": {
      "battery": 64, 
      "batteryVoltage": 3821
    }, 
    "device": "openaps://indy-e1", 
    "_id": "582e2d050e76b898408f1898"
  }
]