[
  {
    "created_at": "2016-11-12T20:13:33.828Z", 
    "mmtune": {
      "scanDetails": [
        [
          "916.564", 
          5, 
          -61
        ], 
        [
          "916.588", 
          5, 
          -56
        ], 
        [
          "916.612", 
          5, 
          -56
        ], 
        [
          "916.636", 
          5, 
          -56
        ], 
        [
          "916.660", 
          5, 
          -57
        ], 
        [
          "916.684", 
          5, 
          -59
        ], 
        [
          "916.708", 
          5, 
          -77
        ]
      ], 
      "setFreq": 916.636, 
      "usedDefault": false, 
      "timestamp": "2016-11-12T20:11:18.000Z"
    }, 
    "pump": {
      "battery": {
        "status": "normal", 
        "voltage": 1.55
      }, 
      "status": {
        "status": "normal", 
        "timestamp": "2016-11-12T20:11:39.000Z", 
        "bolusing": false, 
        "suspended": false
      }, 
      "reservoir": 55.775, 
      "clock": "2016-11-12T12:11:29-08:00"
    }, 
    "openaps": {
      "suggested": {
        "bg": 140, 
        "temp": "absolute", 
        "snoozeBG": 175, 
        "timestamp": "2016-11-12T20:13:25.000Z", 
        "predBGs": {
          "COB": [
            140, 
            143, 
            146, 
            150, 
            153, 
            158, 
            162, 
            166, 
            171, 
            175, 
            179, 
            184, 
            188, 
            192, 
            196, 
            201, 
            205, 
            209, 
            212, 
            216, 
            219, 
            223, 
            226, 
            230, 
            233, 
            237, 
            240, 
            243, 
            247, 
            250, 
            253, 
            256, 
            259, 
            262, 
            265, 
            267, 
            270, 
            272, 
            275, 
            277, 
            278, 
            280, 
            282
          ], 
          "aCOB": [
            140, 
            141, 
            142, 
            144, 
            146, 
            148, 
            150, 
            153, 
            156, 
            159, 
            162, 
            165, 
            168, 
            171, 
            174, 
            178, 
            181, 
            184, 
            187, 
            190, 
            193, 
            196, 
            199, 
            203, 
            206, 
            209, 
            213, 
            216, 
            219, 
            223, 
            226, 
            230, 
            233, 
            237, 
            240, 
            244, 
            247, 
            250, 
            253, 
            257, 
            260, 
            263, 
            265
          ], 
          "IOB": [
            140, 
            142, 
            144, 
            145, 
            146, 
            146, 
            146, 
            145, 
            143, 
            141, 
            138, 
            133, 
            129, 
            124, 
            120, 
            116, 
            112, 
            108, 
            104, 
            100, 
            96, 
            93, 
            90, 
            87, 
            85, 
            83, 
            80, 
            78, 
            77, 
            75, 
            74, 
            73, 
            72, 
            71, 
            70, 
            70, 
            69
          ]
        }, 
        "reason": "COB: 54, Dev: 73, BGI: -8.99, ISF: 83, Target: 112; Eventual BG 282 >= 112, temp 1.75<2.1U/hr, but 26m left and 1.75 ~ req 2.1U/hr: no action required", 
        "COB": 54, 
        "eventualBG": 282, 
        "tick": "+5", 
        "IOB": 1.07
      }, 
      "iob": {
        "netbasalinsulin": 1.4, 
        "timestamp": "2016-11-12T20:11:29.000Z", 
        "activity": 0.0218, 
        "basaliob": 0.619, 
        "hightempinsulin": 1.55, 
        "bolussnooze": 0, 
        "iob": 1.07
      }, 
      "enacted": {
        "bg": 131, 
        "temp": "absolute", 
        "snoozeBG": 157, 
        "recieved": true, 
        "reason": "COB: 56, Dev: 68, BGI: -9.41, ISF: 81, Target: 111; Eventual BG 286 >= 111, temp 1.35<1.75U/hr", 
        "rate": 1.75, 
        "COB": 56, 
        "eventualBG": 286, 
        "timestamp": "2016-11-12T20:07:42.000Z", 
        "duration": 30, 
        "tick": "+6", 
        "IOB": 1.109
      }
    }, 
    "uploader": {
      "battery": 100, 
      "batteryVoltage": 4369
    }, 
    "device": "openaps://indy-e1", 
    "_id": "582777edfcad3eab79e659a9"
  }
]