{
  "bg": 154, 
  "temp": "absolute", 
  "snoozeBG": 127, 
  "recieved": true, 
  "predBGs": {
    "COB": [
      154, 
      155, 
      156, 
      156, 
      155, 
      154, 
      153, 
      151, 
      149, 
      146, 
      143, 
      139, 
      135, 
      132, 
      128, 
      125, 
      121, 
      118, 
      115, 
      113, 
      110, 
      109, 
      107, 
      106, 
      105, 
      105, 
      105, 
      106, 
      107, 
      108, 
      110, 
      112, 
      115, 
      118, 
      121, 
      124, 
      127, 
      130, 
      133, 
      136, 
      139, 
      142, 
      145
    ], 
    "aCOB": [
      154, 
      160, 
      165, 
      170, 
      175, 
      178, 
      181, 
      184, 
      185, 
      186, 
      187, 
      187, 
      187, 
      186, 
      186, 
      185, 
      185, 
      184, 
      184, 
      184, 
      184, 
      184, 
      185, 
      186, 
      187, 
      188, 
      190, 
      191, 
      194, 
      196, 
      199, 
      202, 
      205, 
      208, 
      211, 
      214, 
      217, 
      220, 
      223, 
      225, 
      228, 
      230, 
      232
    ], 
    "IOB": [
      154, 
      155, 
      154, 
      153, 
      152, 
      149, 
      146, 
      141, 
      136, 
      130, 
      123, 
      116, 
      108, 
      100, 
      92, 
      84, 
      77, 
      70, 
      63, 
      56, 
      50, 
      44, 
      39
    ]
  }, 
  "reason": "COB: 45, Dev: 29, BGI: -3.79, ISF: 83, Target: 112; Eventual BG 145 >= 112, 26m@0.750 = 0.325 > req 0.18+20%. Setting temp basal of 0.975U/hr", 
  "rate": 0.975, 
  "COB": 45, 
  "eventualBG": 145, 
  "timestamp": "2016-11-14T16:50:39.976612", 
  "duration": 30, 
  "tick": "+1", 
  "IOB": 1.735
}