[
  {
    "trend_arrow": "45_DOWN", 
    "display_time": "2016-11-18T11:27:05-08:00", 
    "noise": 1, 
    "direction": "FortyFiveDown", 
    "system_time": "2016-11-18T19:14:24-08:00", 
    "sgv": 116, 
    "dateString": "2016-11-18T11:27:05-08:00", 
    "device": "openaps://indy-e1/cgm", 
    "unfiltered": 106384, 
    "rssi": 196, 
    "date": 1479497225000.0, 
    "filtered": 112832, 
    "type": "sgv", 
    "glucose": 116
  }, 
  {
    "trend_arrow": "45_DOWN", 
    "display_time": "2016-11-18T11:22:05-08:00", 
    "noise": 1, 
    "direction": "FortyFiveDown", 
    "system_time": "2016-11-18T19:09:24-08:00", 
    "sgv": 119, 
    "dateString": "2016-11-18T11:22:05-08:00", 
    "device": "openaps://indy-e1/cgm", 
    "unfiltered": 108752, 
    "rssi": 205, 
    "date": 1479496925000.0, 
    "filtered": 118080, 
    "type": "sgv", 
    "glucose": 119
  }, 
  {
    "trend_arrow": "45_DOWN", 
    "display_time": "2016-11-18T11:17:05-08:00", 
    "noise": 1, 
    "direction": "FortyFiveDown", 
    "system_time": "2016-11-18T19:04:24-08:00", 
    "sgv": 127, 
    "dateString": "2016-11-18T11:17:05-08:00", 
    "device": "openaps://indy-e1/cgm", 
    "unfiltered": 114384, 
    "rssi": 200, 
    "date": 1479496625000.0, 
    "filtered": 122368, 
    "type": "sgv", 
    "glucose": 127
  }, 
  {
    "trend_arrow": "FLAT", 
    "display_time": "2016-11-18T11:12:05-08:00", 
    "noise": 1, 
    "direction": "Flat", 
    "system_time": "2016-11-18T18:59:24-08:00", 
    "sgv": 136, 
    "dateString": "2016-11-18T11:12:05-08:00", 
    "device": "openaps://indy-e1/cgm", 
    "unfiltered": 120704, 
    "rssi": 193, 
    "date": 1479496325000.0, 
    "filtered": 124912, 
    "type": "sgv", 
    "glucose": 136
  }, 
  {
    "trend_arrow": "FLAT", 
    "display_time": "2016-11-18T11:07:05-08:00", 
    "noise": 1, 
    "direction": "Flat", 
    "system_time": "2016-11-18T18:54:24-08:00", 
    "sgv": 140, 
    "dateString": "2016-11-18T11:07:05-08:00", 
    "device": "openaps://indy-e1/cgm", 
    "unfiltered": 123648, 
    "rssi": 188, 
    "date": 1479496025000.0, 
    "filtered": 126000, 
    "type": "sgv", 
    "glucose": 140
  }, 
  {
    "trend_arrow": "FLAT", 
    "display_time": "2016-11-18T11:02:05-08:00", 
    "noise": 1, 
    "direction": "Flat", 
    "system_time": "2016-11-18T18:49:24-08:00", 
    "sgv": 143, 
    "dateString": "2016-11-18T11:02:05-08:00", 
    "device": "openaps://indy-e1/cgm", 
    "unfiltered": 125872, 
    "rssi": 188, 
    "date": 1479495725000.0, 
    "filtered": 126576, 
    "type": "sgv", 
    "glucose": 143
  }
]