{
  "device": "openaps://indy-e1", 
  "pump": {
    "battery": {
      "status": "normal", 
      "voltage": 1.56
    }, 
    "status": {
      "status": "normal", 
      "timestamp": "2016-11-17T10:47:25.000Z", 
      "bolusing": false, 
      "suspended": false
    }, 
    "reservoir": 100.85, 
    "clock": "2016-11-17T02:47:16-08:00"
  }, 
  "uploader": {
    "battery": 100, 
    "batteryVoltage": 4370
  }, 
  "openaps": {
    "suggested": {
      "bg": 85, 
      "temp": "absolute", 
      "snoozeBG": 109, 
      "timestamp": "2016-11-17T10:49:12.000Z", 
      "predBGs": {
        "IOB": [
          85, 
          84, 
          84, 
          84, 
          84, 
          84, 
          85, 
          86, 
          88, 
          90, 
          92, 
          94, 
          97, 
          99, 
          102, 
          104, 
          107, 
          109, 
          111, 
          113, 
          115, 
          116, 
          118, 
          119, 
          121, 
          122, 
          123, 
          124, 
          124, 
          125, 
          126, 
          126, 
          126, 
          127
        ]
      }, 
      "reason": "COB: 0, Dev: -13, BGI: 1.08, ISF: 86, Target: 114; Eventual BG 109 < 114, temp 0 ~< req 0.325U/hr", 
      "COB": 0, 
      "eventualBG": 109, 
      "tick": "+2", 
      "IOB": -0.46
    }, 
    "iob": {
      "netbasalinsulin": -0.25, 
      "timestamp": "2016-11-17T10:47:16.000Z", 
      "activity": -0.0025, 
      "basaliob": -0.46, 
      "hightempinsulin": 0.5, 
      "bolussnooze": 0, 
      "iob": -0.46
    }, 
    "enacted": {
      "bg": 89, 
      "temp": "absolute", 
      "snoozeBG": 96, 
      "recieved": true, 
      "rate": 0, 
      "reason": "COB: 0, Dev: -20, BGI: 0.29, ISF: 84, Target: 113; Eventual BG 96 < 113, setting -0.225U/hr", 
      "COB": 0, 
      "eventualBG": 96, 
      "timestamp": "2016-11-17T10:33:27.000Z", 
      "duration": 30, 
      "tick": "+1", 
      "IOB": -0.341
    }
  }, 
  "mmtune": {
    "scanDetails": [
      [
        "916.564", 
        5, 
        -77
      ], 
      [
        "916.588", 
        5, 
        -73
      ], 
      [
        "916.612", 
        4, 
        -78
      ], 
      [
        "916.636", 
        4, 
        -78
      ], 
      [
        "916.660", 
        5, 
        -73
      ], 
      [
        "916.684", 
        5, 
        -76
      ], 
      [
        "916.708", 
        1, 
        -97
      ]
    ], 
    "setFreq": 916.66, 
    "timestamp": "2016-11-17T10:47:04.000Z", 
    "usedDefault": false
  }
}