{
  "device": "openaps://indy-e1", 
  "pump": {
    "battery": {
      "status": "normal", 
      "voltage": 1.53
    }, 
    "status": {
      "status": "normal", 
      "timestamp": "2016-11-18T04:52:26.000Z", 
      "bolusing": false, 
      "suspended": false
    }, 
    "reservoir": 77.225, 
    "clock": "2016-11-17T20:52:18-08:00"
  }, 
  "uploader": {
    "battery": 100, 
    "batteryVoltage": 4362
  }, 
  "openaps": {
    "suggested": {
      "bg": 230, 
      "temp": "absolute", 
      "snoozeBG": 258, 
      "timestamp": "2016-11-18T04:54:18.000Z", 
      "predBGs": {
        "COB": [
          230, 
          239, 
          247, 
          253, 
          258, 
          260, 
          261, 
          259, 
          256, 
          250, 
          243, 
          234, 
          224, 
          214, 
          205, 
          195, 
          186, 
          177, 
          169, 
          161, 
          153, 
          146, 
          139, 
          132, 
          127, 
          122, 
          117, 
          113, 
          109, 
          107, 
          104, 
          102, 
          100, 
          99, 
          98, 
          97, 
          96
        ], 
        "aCOB": [
          230, 
          232, 
          233, 
          235, 
          235, 
          235, 
          234, 
          232, 
          229, 
          225, 
          220, 
          215, 
          209, 
          204, 
          198, 
          191, 
          185, 
          178, 
          171, 
          164, 
          157, 
          150, 
          143, 
          136, 
          131, 
          126, 
          121, 
          117, 
          114, 
          111, 
          108, 
          106, 
          104, 
          103, 
          102, 
          101, 
          101, 
          100
        ], 
        "IOB": [
          230, 
          239, 
          247, 
          253, 
          258, 
          261, 
          262, 
          261, 
          258, 
          252, 
          246, 
          237, 
          227, 
          217, 
          208, 
          198, 
          189, 
          181, 
          172, 
          164, 
          156, 
          149, 
          142, 
          136, 
          130, 
          125, 
          120, 
          116, 
          113, 
          110, 
          107, 
          105, 
          103, 
          102, 
          101, 
          100, 
          100, 
          99
        ]
      }, 
      "reason": "COB: 18, Dev: 110, BGI: -7.62, ISF: 83, Target: 80; Eventual BG 182 >= 80, temp 2.85<3.2U/hr, but 25m left and 2.85 ~ req 3.2U/hr: no action required", 
      "COB": 18, 
      "eventualBG": 182, 
      "tick": "+14", 
      "IOB": 1.9
    }, 
    "iob": {
      "netbasalinsulin": 1.25, 
      "timestamp": "2016-11-18T04:52:18.000Z", 
      "activity": 0.0183, 
      "basaliob": 0.886, 
      "hightempinsulin": 1.55, 
      "bolussnooze": 0.606, 
      "iob": 1.9
    }, 
    "enacted": {
      "bg": 180, 
      "temp": "absolute", 
      "snoozeBG": 118, 
      "recieved": true, 
      "rate": 0.775, 
      "reason": "COB: 24, Dev: 1, BGI: -8.21, ISF: 83, Target: 80; Eventual BG 39 < 80, bolus snooze: eventual BG range 39-118; setting current basal of 0.775 as temp", 
      "COB": 24, 
      "eventualBG": 39, 
      "timestamp": "2016-11-18T04:42:42.000Z", 
      "duration": 30, 
      "tick": -8, 
      "IOB": 1.924
    }
  }, 
  "mmtune": {
    "scanDetails": [
      [
        "916.540", 
        5, 
        -81
      ], 
      [
        "916.564", 
        5, 
        -73
      ], 
      [
        "916.588", 
        5, 
        -72
      ], 
      [
        "916.612", 
        5, 
        -75
      ], 
      [
        "916.636", 
        5, 
        -74
      ], 
      [
        "916.660", 
        5, 
        -77
      ], 
      [
        "916.684", 
        5, 
        -80
      ]
    ], 
    "setFreq": 916.588, 
    "timestamp": "2016-11-18T04:52:05.000Z", 
    "usedDefault": false
  }
}